[
  {
    "slug": "tailwind-dicas",
    "title": "Tailwind CSS Produtivo",
    "description": "Classes utilitárias que economizam horas de trabalho.",
    "tags": ["css", "tailwind"],
    "publishedAt": "2026-03-10",
    "status": "published",
    "authors": ["erivelton", "maria"],
    "series": "css-master",
    "order": 1,
    "hasCover": true,
    "readingTime": 6,
    "filePath": "content/posts/2026-03-10-tailwind-dicas/index.mdx"
  },
  {
    "slug": "performance-web",
    "title": "Web Vitals e Performance",
    "description": "Como bater 100 no Lighthouse com Next.js.",
    "tags": ["performance", "nextjs"],
    "publishedAt": "2026-03-09",
    "status": "published",
    "authors": ["erivelton"],
    "series": "css-master",
    "order": 2,
    "hasCover": false,
    "readingTime": 1,
    "filePath": "content/posts/2026-03-09-performance-web/index.mdx"
  },
  {
    "slug": "zod-validacao",
    "title": "Segurança com Zod",
    "description": "Validando entradas de usuários e contratos de API.",
    "tags": ["typescript", "backend", "zod"],
    "publishedAt": "2026-03-08",
    "status": "published",
    "authors": ["erivelton"],
    "hasCover": false,
    "readingTime": 1,
    "filePath": "content/posts/2026-03-08-zod-validacao/index.mdx"
  },
  {
    "slug": "api-routes",
    "title": "Criando API Routes",
    "description": "Backend dentro do Next.js de forma simplificada.",
    "tags": ["nextjs", "backend"],
    "publishedAt": "2026-03-06",
    "status": "published",
    "authors": ["erivelton"],
    "hasCover": false,
    "readingTime": 1,
    "filePath": "content/posts/2026-03-06-api-routes/index.mdx"
  }
]
